<?xml version="1.0" ?>
<bugrepository name="androR2">
   <bug fixdate="" id="1428" opendate="">
      <buginformation>
         <summary/>
         <description>main activity body part list fragment body part detail fragment action bar root content drawer layout action toolbar image profile action chrono fragment container add body part list bodypart logo list bodypart list bodypart minigraph list bodypart lastrecord status bar background navigation bar background body tracking details toolbar delete button name card view bodypart logo bodypart name value text view button add bodymeasure chart editor value title editor value date input cardview weight singlevalueinput title singlevalueinput value editor value input singlevalueinput unit spinner text btn cancel btn update</description>
      </buginformation>
      <fixedFiles>
         <file>com.easyfitness.fonte.FonteGraphFragment.java</file>
         <file>com.easyfitness.DAO.bodymeasures.BodyPart.java</file>
         <file>com.easyfitness.graph.DateGraph.java</file>
         <file>com.easyfitness.machines.MachineArrayFullAdapter.java</file>
         <file>com.easyfitness.machines.MachineDetailsFragment.java</file>
         <file>com.easyfitness.machines.MachineCursorAdapter.java</file>
         <file>com.easyfitness.machines.MachineFragment.java</file>
         <file>com.easyfitness.DAO.bodymeasures.BodyPartExtensions.java</file>
         <file>com.easyfitness.ValueEditorDialogbox.java</file>
         <file>com.easyfitness.bodymeasures.BodyPartDetailsFragment.java</file>
      </fixedFiles>
   </bug>
</bugrepository>
